tarea3/__init__.py
tarea3/principal.py
tarea3/controladores/__init__.py
tarea3/controladores/conexion.py
tarea3/controladores/mostrarReservas.py
tarea3/controladores/reservar.py
tarea3/img/__init__.py
tarea3/img/cartel-de-hotel.png
tarea3/img/cita.png
tarea3/img/imagenes_rc.py
tarea3/modelo/reservas.db
tarea3/vistas/MostrarReservas_ui.py
tarea3/vistas/Reservar_ui.py
tarea3/vistas/__init__.py
tarea3-1.0.0.dist-info/METADATA
tarea3-1.0.0.dist-info/WHEEL
tarea3-1.0.0.dist-info/entry_points.txt
tarea3-1.0.0.dist-info/top_level.txt
tarea3-1.0.0.dist-info/RECORD
