Metadata-Version: 2.4
Name: tarea3
Version: 1.0.0
Summary: Gestión de reservas
Author: cristian zola ndongala ndele nzinga
Requires-Dist: PySide6
Dynamic: author
Dynamic: requires-dist
Dynamic: summary
